README.rst
regpath.py
setup.py
regpath.egg-info/PKG-INFO
regpath.egg-info/SOURCES.txt
regpath.egg-info/dependency_links.txt
regpath.egg-info/top_level.txt
test/test_regpath.py