Metadata-Version: 1.1
Name: regpath
Version: 0.1.0
Summary: regpath - pathlib and winreg
Home-page: https://github.com/chrono-meter/regpath
Author: chrono-meter@gmx.net
Author-email: chrono-meter@gmx.net
License: PSF
Download-URL: http://pypi.python.org/pypi/regpath
Platform: UNKNOWN
Classifier: Development Status :: 4 - Beta
Classifier: Environment :: Win32 (MS Windows)
Classifier: Intended Audience :: Developers
Classifier: License :: OSI Approved :: Python Software Foundation License
Classifier: Operating System :: Microsoft :: Windows
Classifier: Programming Language :: Python :: 3.4
Classifier: Programming Language :: Python :: 3.5
Classifier: Topic :: Software Development :: Libraries :: Python Modules
